TOPSIS.py
TOPSIS_SatvikMehra_101803278-0.0.1.dist-info/LICENSE.txt
TOPSIS_SatvikMehra_101803278-0.0.1.dist-info/METADATA
TOPSIS_SatvikMehra_101803278-0.0.1.dist-info/WHEEL
TOPSIS_SatvikMehra_101803278-0.0.1.dist-info/top_level.txt
TOPSIS_SatvikMehra_101803278-0.0.1.dist-info/RECORD
